Metadata-Version: 2.1
Name: geotorch
Version: 0.3.0
Summary: Constrained Optimization and Manifold Optimization in Pytorch
Home-page: https://github.com/Lezcano/geotorch
Author: Mario Lezcano Casado
Author-email: lezcano-93@hotmail.com
License: MIT
Keywords: Constrained Optimization,Optimization on Manifolds,Pytorch
Platform: UNKNOWN
Classifier: Development Status :: 3 - Alpha
Classifier: Programming Language :: Python
Classifier: Programming Language :: Python :: 3
Classifier: Programming Language :: Python :: 3.5
Classifier: License :: OSI Approved :: MIT License
Classifier: Topic :: Scientific/Engineering
Classifier: Topic :: Scientific/Engineering :: Mathematics
Classifier: Intended Audience :: Science/Research
Classifier: Intended Audience :: Developers
Classifier: Operating System :: OS Independent
Requires-Python: >=3.5
License-File: LICENSE
Requires-Dist: torch (>=1.9)
Provides-Extra: dev
Requires-Dist: pytest ; extra == 'dev'
Requires-Dist: black ; extra == 'dev'
Requires-Dist: flake8 ; extra == 'dev'
Requires-Dist: sphinx ; extra == 'dev'
Requires-Dist: sphinx-autodoc-typehints ; extra == 'dev'
Requires-Dist: sphinx-rtd-theme ; extra == 'dev'
Requires-Dist: sphinxcontrib-spelling ; extra == 'dev'
Requires-Dist: codecov ; extra == 'dev'
Provides-Extra: test
Requires-Dist: pytest ; extra == 'test'
